med2nlp/__init__.py
med2nlp/_nbdev.py
med2nlp/core.py
med2nlp-0.0.1.dist-info/LICENSE
med2nlp-0.0.1.dist-info/METADATA
med2nlp-0.0.1.dist-info/WHEEL
med2nlp-0.0.1.dist-info/entry_points.txt
med2nlp-0.0.1.dist-info/top_level.txt
med2nlp-0.0.1.dist-info/RECORD
