Metadata-Version: 2.1
Name: med2nlp
Version: 0.0.1
Summary: MED(Minimum Effective Dose) to NLP
Home-page: https://github.com/Daniel-R_Armstrong/med2nlp
Author: Daniel R. Armstrong
Author-email: Armstrong.daniel.robert@gmail.com
License: Apache Software License 2.0
Keywords: NLP,Deep Learning,Fastai,Pytorch,BERT,RoBERTa,XLNet,XLM,DistilBERT,ABSA,
Platform: UNKNOWN
Classifier: Development Status :: 3 - Alpha
Classifier: Intended Audience :: Developers
Classifier: License :: OSI Approved :: Apache Software License
Classifier: Natural Language :: English
Classifier: Programming Language :: Python :: 3.6
Classifier: Programming Language :: Python :: 3.7
Classifier: Programming Language :: Python :: 3.8
Requires-Python: >=3.6
